datreant.data-0.7.1-py3.6-nspkg.pth
datreant/data/__init__.py
datreant/data/agglimbs.py
datreant/data/attach.py
datreant/data/core.py
datreant/data/limbs.py
datreant/data/npdata.py
datreant/data/pddata.py
datreant/data/pydata.py
datreant/data/tests/__init__.py
datreant/data/tests/test_bundle.py
datreant/data/tests/test_data.py
datreant/data/tests/test_locks.py
datreant/data/tests/test_treants.py
datreant.data-0.7.1.dist-info/METADATA
datreant.data-0.7.1.dist-info/RECORD
datreant.data-0.7.1.dist-info/WHEEL
datreant.data-0.7.1.dist-info/namespace_packages.txt
datreant.data-0.7.1.dist-info/top_level.txt
