Metadata-Version: 2.1
Name: datreant.data
Version: 0.7.1
Summary: convenient data storage and retrieval in HDF5 for Treants
Home-page: http://datreant.org/
Author: David Dotson
Author-email: dotsdl@gmail.com
License: BSD
Platform: UNKNOWN
Classifier: Development Status :: 3 - Alpha
Classifier: Environment :: Console
Classifier: Intended Audience :: Science/Research
Classifier: License :: OSI Approved :: BSD License
Classifier: Operating System :: POSIX
Classifier: Programming Language :: Python
Classifier: Topic :: Scientific/Engineering
Classifier: Topic :: Software Development :: Libraries :: Python Modules
Requires-Dist: datreant.core (==0.7.1)
Requires-Dist: six
Requires-Dist: numpy
Requires-Dist: pandas
Requires-Dist: tables
Requires-Dist: h5py
